wake_assets
