Metadata-Version: 1.0
Name: wake-assets
Version: 0.3.0
Summary: Python HTML helper for assets managed by wake
Home-page: http://github.com/jcoglan/wake-assets-python
Author: James Coglan
Author-email: jcoglan@gmail.com
License: UNKNOWN
Platform: UNKNOWN
